README.txt
setup.py
darts/__init__.py
darts.util.lru.egg-info/PKG-INFO
darts.util.lru.egg-info/SOURCES.txt
darts.util.lru.egg-info/dependency_links.txt
darts.util.lru.egg-info/namespace_packages.txt
darts.util.lru.egg-info/top_level.txt
darts.util.lru.egg-info/zip-safe
darts/lib/__init__.py
darts/lib/utils/__init__.py
darts/lib/utils/lru.py