Metadata-Version: 1.0
Name: darts.util.lru
Version: 0.5
Summary: Simple dictionary with LRU behaviour
Home-page: UNKNOWN
Author: Deterministic Arts
Author-email: contact@deterministic-arts.de
License: MIT
Platform: UNKNOWN
